ogd/common/__init__.py
ogd/common/configs/Config.py
ogd/common/configs/DataTableConfig.py
ogd/common/configs/TestConfig.py
ogd/common/configs/__init__.py
ogd/common/configs/storage/BigQueryConfig.py
ogd/common/configs/storage/DataStoreConfig.py
ogd/common/configs/storage/DatasetRepositoryConfig.py
ogd/common/configs/storage/DictionaryStoreConfig.py
ogd/common/configs/storage/FileStoreConfig.py
ogd/common/configs/storage/MySQLConfig.py
ogd/common/configs/storage/RepositoryIndexingConfig.py
ogd/common/configs/storage/SSHConfig.py
ogd/common/configs/storage/__init__.py
ogd/common/configs/storage/credentials/CredentialConfig.py
ogd/common/configs/storage/credentials/EmptyCredential.py
ogd/common/configs/storage/credentials/KeyCredentialConfig.py
ogd/common/configs/storage/credentials/PasswordCredentialConfig.py
ogd/common/configs/storage/credentials/__init__.py
ogd/common/filters/Filter.py
ogd/common/filters/NoFilter.py
ogd/common/filters/RangeFilter.py
ogd/common/filters/SetFilter.py
ogd/common/filters/__init__.py
ogd/common/filters/collections/DatasetFilterCollection.py
ogd/common/filters/collections/EventFilterCollection.py
ogd/common/filters/collections/IDFilterCollection.py
ogd/common/filters/collections/SequencingFilterCollection.py
ogd/common/filters/collections/VersioningFilterCollection.py
ogd/common/filters/collections/__init__.py
ogd/common/models/DatasetKey.py
ogd/common/models/Event.py
ogd/common/models/EventSet.py
ogd/common/models/Feature.py
ogd/common/models/FeatureSet.py
ogd/common/models/GameData.py
ogd/common/models/SemanticVersion.py
ogd/common/models/__init__.py
ogd/common/models/coding/Code.py
ogd/common/models/coding/Coder.py
ogd/common/models/enums/ElementMappingType.py
ogd/common/models/enums/ExportMode.py
ogd/common/models/enums/ExtractionMode.py
ogd/common/models/enums/FilterMode.py
ogd/common/models/enums/IDMode.py
ogd/common/models/enums/IterationMode.py
ogd/common/models/enums/VersionType.py
ogd/common/models/enums/__init__.py
opengamedata_common-2.0.10.dist-info/LICENSE
opengamedata_common-2.0.10.dist-info/METADATA
opengamedata_common-2.0.10.dist-info/WHEEL
opengamedata_common-2.0.10.dist-info/top_level.txt
opengamedata_common-2.0.10.dist-info/RECORD
